connector_definition_runner/__init__.py
connector_definition_runner/__version__.py
connector_definition_runner/attachments.py
connector_definition_runner/authenticate.py
connector_definition_runner/runner.py
connector_def_runner-2.3.10.dist-info/LICENSE
connector_def_runner-2.3.10.dist-info/METADATA
connector_def_runner-2.3.10.dist-info/WHEEL
connector_def_runner-2.3.10.dist-info/RECORD
