Metadata-Version: 2.3
Name: connector_def_runner
Version: 2.3.10
Summary: Run connectors by schema definitions
Keywords: connector,swimlane,connectors
Author: Swimlane
Author-email: integrations@swimlane.com
Maintainer: Swimlane
Maintainer-email: integrations@swimlane.com
Requires-Python: >=3.9,<4.0
Classifier: Programming Language :: Python :: 3
Classifier: Programming Language :: Python :: 3.9
Classifier: Programming Language :: Python :: 3.10
Classifier: Programming Language :: Python :: 3.11
Classifier: Programming Language :: Python :: 3.12
Classifier: License :: OSI Approved :: MIT License
Classifier: Operating System :: OS Independent
Requires-Dist: PyYAML (==6.0.2)
Requires-Dist: chevron (==0.14.0)
Requires-Dist: requests (==2.32.3)
Requires-Dist: xmltodict (==0.14.2)
